{
 "actions": [],
 "allow_rename": 1,
 "creation": "2025-03-28 17:15:35.808487",
 "doctype": "DocType",
 "editable_grid": 1,
 "engine": "InnoDB",
 "field_order": [
  "section_break_xx9b",
  "from",
  "to",
  "amount",
  "is_paid"
 ],
 "fields": [
  {
   "fieldname": "section_break_xx9b",
   "fieldtype": "Section Break"
  },
  {
   "fieldname": "amount",
   "fieldtype": "Currency",
   "in_list_view": 1,
   "label": "Amount"
  },
  {
   "default": "0",
   "fieldname": "is_paid",
   "fieldtype": "Check",
   "in_list_view": 1,
   "label": "Is Paid"
  },
  {
   "fieldname": "from",
   "fieldtype": "Date",
   "hide_seconds": 1,
   "in_list_view": 1,
   "label": "From"
  },
  {
   "fieldname": "to",
   "fieldtype": "Date",
   "in_list_view": 1,
   "label": "To"
  }
 ],
 "grid_page_length": 50,
 "index_web_pages_for_search": 1,
 "istable": 1,
 "links": [],
 "modified": "2025-03-28 18:34:04.902714",
 "modified_by": "Administrator",
 "module": "Mewacho",
 "name": "Mewacho Payment Term",
 "owner": "Administrator",
 "permissions": [],
 "row_format": "Dynamic",
 "sort_field": "creation",
 "sort_order": "DESC",
 "states": []
}
